custom/__init__.py
custom/custom.py
custom/data/CUSTOM_codon_weights.csv
custom/data/CUSTOM_codonfreq_CoCoPuts.csv
custom/data/CUSTOM_codonpairsfreq_CoCoPuts.csv
custom/data/CUSTOM_tissue_ratios.csv
custom_optimizer-0.0.1.dist-info/LICENSE
custom_optimizer-0.0.1.dist-info/METADATA
custom_optimizer-0.0.1.dist-info/WHEEL
custom_optimizer-0.0.1.dist-info/top_level.txt
custom_optimizer-0.0.1.dist-info/RECORD
